ayleea/Std_Json.py
ayleea/Std_Json_Tools.py
ayleea/__init__.py
ayleea-0.2.2.dist-info/METADATA
ayleea-0.2.2.dist-info/WHEEL
ayleea-0.2.2.dist-info/top_level.txt
ayleea-0.2.2.dist-info/RECORD
