Metadata-Version: 2.4
Name: ayleea
Version: 0.2.2
Summary: An Std Json Tool
Requires-Python: >=3.10
Requires-Dist: pandas
Requires-Dist: ujson
Requires-Dist: tqdm
Requires-Dist: opencv-python
